extrap/__init__.py
extrap/__main__.py
extrap/entities/__init__.py
extrap/entities/callpath.py
extrap/entities/calltree.py
extrap/entities/coordinate.py
extrap/entities/experiment.py
extrap/entities/fraction.py
extrap/entities/functions.py
extrap/entities/hypotheses.py
extrap/entities/measurement.py
extrap/entities/metric.py
extrap/entities/model.py
extrap/entities/named_entity.py
extrap/entities/parameter.py
extrap/entities/scaling_type.py
extrap/entities/terms.py
extrap/entities/annotations/__init__.py
extrap/entities/annotations/comment_annotation/__init__.py
extrap/entities/annotations/comment_annotation/comment_base.svg
extrap/extrap/__init__.py
extrap/extrap/extrapcmd.py
extrap/extrap/extrapgui.py
extrap/fileio/__init__.py
extrap/fileio/experiment_io.py
extrap/fileio/io_helper.py
extrap/fileio/output.py
extrap/fileio/values_io.py
extrap/fileio/file_reader/__init__.py
extrap/fileio/file_reader/abstract_directory_reader.py
extrap/fileio/file_reader/cube_file_reader2.py
extrap/fileio/file_reader/extrap3_experiment_reader.py
extrap/fileio/file_reader/file_reader_mixin.py
extrap/fileio/file_reader/json_file_reader.py
extrap/fileio/file_reader/jsonlines_file_reader.py
extrap/fileio/file_reader/talpas_file_reader.py
extrap/fileio/file_reader/text_file_reader.py
extrap/gui/AdvancedPlotWidget.py
extrap/gui/ColorWidget.py
extrap/gui/DataDisplay.py
extrap/gui/GraphWidget.py
extrap/gui/ImportOptionsDialog.py
extrap/gui/LogWidget.py
extrap/gui/MainWidget.py
extrap/gui/MeasurementWizardWidget.py
extrap/gui/ModelerOptionsWidget.py
extrap/gui/ModelerWidget.py
extrap/gui/PlotTypeSelector.py
extrap/gui/SelectorWidget.py
extrap/gui/StrongScalingConversionDialog.py
extrap/gui/TreeModel.py
extrap/gui/TreeView.py
extrap/gui/Utils.py
extrap/gui/__init__.py
extrap/gui/components/ExpanderWidget.py
extrap/gui/components/ParameterValueSlider.py
extrap/gui/components/ProgressWindow.py
extrap/gui/components/__init__.py
extrap/gui/components/annotation_delegate.py
extrap-4.2.3.dist-info/AUTHORS.md
extrap-4.2.3.dist-info/LICENSE
extrap-4.2.3.dist-info/METADATA
extrap-4.2.3.dist-info/WHEEL
extrap-4.2.3.dist-info/entry_points.txt
extrap-4.2.3.dist-info/top_level.txt
extrap-4.2.3.dist-info/RECORD
