Metadata-Version: 2.1
Name: extrap
Version: 4.2.3
Summary: Extra-P, automated performance modeling for HPC applications
Home-page: https://github.com/extra-p/extrap
Author: Extra-P project
Author-email: extra-p@lists.parallel.informatik.tu-darmstadt.de
Classifier: Development Status :: 5 - Production/Stable
Classifier: License :: OSI Approved :: BSD License
Classifier: Operating System :: OS Independent
Classifier: Programming Language :: Python :: 3
Classifier: Programming Language :: Python :: 3 :: Only
Classifier: Programming Language :: Python :: 3.8
Classifier: Programming Language :: Python :: 3.9
Classifier: Programming Language :: Python :: 3.10
Classifier: Programming Language :: Python :: 3.11
Classifier: Programming Language :: Python :: 3.12
Classifier: Operating System :: OS Independent
Classifier: Intended Audience :: Developers
Classifier: Intended Audience :: Science/Research
Classifier: Topic :: Scientific/Engineering
Classifier: Topic :: Software Development
Classifier: Topic :: Software Development :: Libraries :: Python Modules
Requires-Python: >=3.8
License-File: LICENSE
License-File: AUTHORS.md
Requires-Dist: PySide6-Essentials~=6.4
Requires-Dist: numpy~=1.18
Requires-Dist: matplotlib~=3.6
Requires-Dist: tqdm~=4.47
Requires-Dist: pycubexr!=2.0.0,<3,>=1.2.3
Requires-Dist: marshmallow~=3.7
Requires-Dist: packaging>=20.0
Requires-Dist: pyobjc-framework-Cocoa~=9.0; sys_platform == "darwin"
Requires-Dist: scikit-learn>=1.2.2
Provides-Extra: adaptive-modeling
Requires-Dist: extrap-adaptive-modeler<3,>=1.0.2; extra == "adaptive-modeling"
